cyberfusion/ClusterSupport/__init__.py
cyberfusion/ClusterSupport/_interfaces.py
cyberfusion/ClusterSupport/api_keys.py
cyberfusion/ClusterSupport/api_users.py
cyberfusion/ClusterSupport/api_users_to_clusters.py
cyberfusion/ClusterSupport/basic_authentication_realms.py
cyberfusion/ClusterSupport/borg_archive_contents.py
cyberfusion/ClusterSupport/borg_archives.py
cyberfusion/ClusterSupport/borg_repositories.py
cyberfusion/ClusterSupport/certificate_managers.py
cyberfusion/ClusterSupport/certificates.py
cyberfusion/ClusterSupport/cluster_ip_addresses_products.py
cyberfusion/ClusterSupport/clusters.py
cyberfusion/ClusterSupport/clusters_cephfs_credentials.py
cyberfusion/ClusterSupport/clusters_rabbitmq_credentials.py
cyberfusion/ClusterSupport/cmses.py
cyberfusion/ClusterSupport/crons.py
cyberfusion/ClusterSupport/custom_config_snippets.py
cyberfusion/ClusterSupport/custom_configs.py
cyberfusion/ClusterSupport/customer_ip_addresses_products.py
cyberfusion/ClusterSupport/customers.py
cyberfusion/ClusterSupport/daemons.py
cyberfusion/ClusterSupport/database_user_grants.py
cyberfusion/ClusterSupport/database_users.py
cyberfusion/ClusterSupport/databases.py
cyberfusion/ClusterSupport/databases_usages.py
cyberfusion/ClusterSupport/domain_routers.py
cyberfusion/ClusterSupport/enums.py
cyberfusion/ClusterSupport/firewall_groups.py
cyberfusion/ClusterSupport/firewall_rules.py
cyberfusion/ClusterSupport/fpm_pools.py
cyberfusion/ClusterSupport/ftp_users.py
cyberfusion/ClusterSupport/haproxy_listens.py
cyberfusion/ClusterSupport/haproxy_listens_to_nodes.py
cyberfusion/ClusterSupport/hosts_entries.py
cyberfusion/ClusterSupport/htpasswd_files.py
cyberfusion/ClusterSupport/htpasswd_users.py
cyberfusion/ClusterSupport/logs.py
cyberfusion/ClusterSupport/mail_accounts.py
cyberfusion/ClusterSupport/mail_accounts_usages.py
cyberfusion/ClusterSupport/mail_aliases.py
cyberfusion/ClusterSupport/mail_domains.py
cyberfusion/ClusterSupport/mail_hostnames.py
python3_cyberfusion_cluster_support-3.9.1.dist-info/METADATA
python3_cyberfusion_cluster_support-3.9.1.dist-info/WHEEL
python3_cyberfusion_cluster_support-3.9.1.dist-info/top_level.txt
python3_cyberfusion_cluster_support-3.9.1.dist-info/RECORD
