Metadata-Version: 2.4
Name: python3-cyberfusion-cluster-support
Version: 3.9.1
Summary: API library for Core API.
Author-email: Cyberfusion <support@cyberfusion.io>
Project-URL: Source, https://vcs.cyberfusion.nl/core/python3-cyberfusion-cluster-support
Requires-Dist: python3-cyberfusion-common~=2.11
Requires-Dist: python3-cyberfusion-cluster-apicli~=3.1
Requires-Dist: python3-cyberfusion-systemd-support~=2.0
Requires-Dist: cached_property==1.5.2
Requires-Dist: factory_boy==2.11.1
Requires-Dist: humanize==4.4.0
Requires-Dist: rich==13.3.1
